tanjiro/YouTube.py
tanjiro/__init__.py
tanjiro/chatbot.py
tanjiro/chatgpt.py
tanjiro/maths.py
tanjiro-0.2.3.dist-info/METADATA
tanjiro-0.2.3.dist-info/WHEEL
tanjiro-0.2.3.dist-info/top_level.txt
tanjiro-0.2.3.dist-info/RECORD
