Metadata-Version: 2.1
Name: tanjiro
Version: 0.2.3
Summary: A simple library to interact with various APIs including ChatGPT, YouTube, Instagram, and more.
Home-page: https://github.com/tanjiro-851/tanjiro
Author: Vikas
Author-email: vgboss91@gmail.com
Classifier: Programming Language :: Python :: 3
Classifier: License :: OSI Approved :: MIT License
Classifier: Operating System :: OS Independent
Requires-Python: >=3.6
Requires-Dist: requests
Requires-Dist: undetected-chromedriver
Requires-Dist: selenium
Requires-Dist: yt-dlp
